divar/__init__.py
divar/client.py
divar_scraper-0.1.1.dist-info/METADATA
divar_scraper-0.1.1.dist-info/WHEEL
divar_scraper-0.1.1.dist-info/top_level.txt
divar_scraper-0.1.1.dist-info/RECORD
