Metadata-Version: 2.1
Name: divar-scraper
Version: 0.1.1
Summary: Python package for crawling from Divar website
Home-page: https://github.com/softcoder24/divar
Author: soft_coder
License: apache-2.0
Platform: UNKNOWN
Classifier: Programming Language :: Python :: 3
Classifier: License :: OSI Approved :: Apache Software License
Classifier: Operating System :: OS Independent
Requires-Python: >=3.6
Requires-Dist: requests
